kivy_deps/__init__.py
kivy_deps/gstreamer_dev/__init__.py
kivy_deps_gstreamer_dev-0.3.4.data/data/include/glib-object.h
kivy_deps_gstreamer_dev-0.3.4.data/data/include/glib-unix.h
kivy_deps_gstreamer_dev-0.3.4.data/data/include/glib.h
kivy_deps_gstreamer_dev-0.3.4.data/data/include/glibconfig.h
kivy_deps_gstreamer_dev-0.3.4.data/data/include/gmodule.h
kivy_deps_gstreamer_dev-0.3.4.data/data/include/msvc_recommended_pragmas.h
kivy_deps_gstreamer_dev-0.3.4.data/data/include/gio/gaction.h
kivy_deps_gstreamer_dev-0.3.4.data/data/include/gio/gactiongroup.h
kivy_deps_gstreamer_dev-0.3.4.data/data/include/gio/gactiongroupexporter.h
kivy_deps_gstreamer_dev-0.3.4.data/data/include/gio/gactionmap.h
kivy_deps_gstreamer_dev-0.3.4.data/data/include/gio/gappinfo.h
kivy_deps_gstreamer_dev-0.3.4.data/data/include/gio/gapplication.h
kivy_deps_gstreamer_dev-0.3.4.data/data/include/gio/gapplicationcommandline.h
kivy_deps_gstreamer_dev-0.3.4.data/data/include/gio/gasyncinitable.h
kivy_deps_gstreamer_dev-0.3.4.data/data/include/gio/gasyncresult.h
kivy_deps_gstreamer_dev-0.3.4.data/data/include/gio/gbufferedinputstream.h
kivy_deps_gstreamer_dev-0.3.4.data/data/include/gio/gbufferedoutputstream.h
kivy_deps_gstreamer_dev-0.3.4.data/data/include/gio/gbytesicon.h
kivy_deps_gstreamer_dev-0.3.4.data/data/include/gio/gcancellable.h
kivy_deps_gstreamer_dev-0.3.4.data/data/include/gio/gcharsetconverter.h
kivy_deps_gstreamer_dev-0.3.4.data/data/include/gio/gcontenttype.h
kivy_deps_gstreamer_dev-0.3.4.data/data/include/gio/gconverter.h
kivy_deps_gstreamer_dev-0.3.4.data/data/include/gio/gconverterinputstream.h
kivy_deps_gstreamer_dev-0.3.4.data/data/include/gio/gconverteroutputstream.h
kivy_deps_gstreamer_dev-0.3.4.data/data/include/gio/gcredentials.h
kivy_deps_gstreamer_dev-0.3.4.data/data/include/gio/gdatagrambased.h
kivy_deps_gstreamer_dev-0.3.4.data/data/include/gio/gdatainputstream.h
kivy_deps_gstreamer_dev-0.3.4.data/data/include/gio/gdataoutputstream.h
kivy_deps_gstreamer_dev-0.3.4.dist-info/METADATA
kivy_deps_gstreamer_dev-0.3.4.dist-info/WHEEL
kivy_deps_gstreamer_dev-0.3.4.dist-info/top_level.txt
kivy_deps_gstreamer_dev-0.3.4.dist-info/RECORD
