Metadata-Version: 2.4
Name: kivy_deps.gstreamer_dev
Version: 0.3.4
Summary: Repackaged binary dependency of Kivy.
Home-page: http://kivy.org/
Author: Kivy Team and other contributors
Author-email: kivy-dev@googlegroups.com
License: LGPL
Dynamic: author
Dynamic: author-email
Dynamic: home-page
Dynamic: license
Dynamic: summary
